schemez/__init__.py
schemez/bind_kwargs.py
schemez/code.py
schemez/code_generation/__init__.py
schemez/code_generation/namespace_callable.py
schemez/code_generation/route_helpers.py
schemez/code_generation/tool_code_generator.py
schemez/code_generation/toolset_code_generator.py
schemez/commented_yaml.py
schemez/convert.py
schemez/docstrings.py
schemez/functionschema/__init__.py
schemez/functionschema/executable.py
schemez/functionschema/functionschema.py
schemez/functionschema/helpers.py
schemez/functionschema/schema_generators.py
schemez/functionschema/typedefs.py
schemez/generators.py
schemez/helpers.py
schemez/log.py
schemez/markdown.py
schemez/openapi/__init__.py
schemez/openapi/callable_factory.py
schemez/openapi/loader.py
schemez/openapi/resolver.py
schemez/py.typed
schemez/pydantic_types.py
schemez/schema.py
schemez/schema_to_type/__init__.py
schemez/schema_to_type/main_impl.py
schemez/schema_to_type/marvin_impl.py
schemez/schema_to_type/simple_impl.py
schemez/schemadef/__init__.py
schemez/schemadef/schemadef.py
schemez/storage/__init__.py
schemez/storage/model_store.py
schemez/tool_executor/__init__.py
schemez/tool_executor/executor.py
schemez/tool_executor/helpers.py
schemez/tool_executor/types.py
schemez-2.2.27.dist-info/licenses/LICENSE
schemez-2.2.27.dist-info/WHEEL
schemez-2.2.27.dist-info/entry_points.txt
schemez-2.2.27.dist-info/METADATA
schemez-2.2.27.dist-info/RECORD
