Metadata-Version: 2.4
Name: schemez
Version: 2.2.27
Summary: Pydantic shim for config stuff
Keywords: code-generation,configuration,data-models,function-calling,json-schema,llm,openai,pydantic,schema,serialization,tool-use,type-hints,validation,yaml
Author: Philipp Temminghoff
Author-email: Philipp Temminghoff <philipptemminghoff@googlemail.com>
License-Expression: MIT
License-File: LICENSE
Classifier: Development Status :: 4 - Beta
Classifier: Framework :: Pydantic
Classifier: Framework :: Pydantic :: 2
Classifier: Intended Audience :: Developers
Classifier: Operating System :: OS Independent
Classifier: Programming Language :: Python :: 3
Classifier: Programming Language :: Python :: 3 :: Only
Classifier: Programming Language :: Python :: 3.12
Classifier: Programming Language :: Python :: 3.13
Classifier: Programming Language :: Python :: 3.14
Classifier: Topic :: Documentation
Classifier: Topic :: Software Development
Classifier: Topic :: Utilities
Classifier: Typing :: Typed
Requires-Dist: docstring-parser>=0.17.0
Requires-Dist: griffe>=1.7.3
Requires-Dist: pydantic
Requires-Dist: universal-pathlib>=0.2.6
Requires-Dist: agentpool ; extra == 'ai'
Requires-Dist: anyenv>=0.4.14 ; extra == 'ai'
Requires-Dist: datamodel-code-generator[ruff] ; extra == 'codegen'
Requires-Dist: jinja2>=3.1.0 ; extra == 'markdown'
Requires-Dist: aiosqlite>=0.20.0 ; extra == 'storage'
Requires-Dist: fastapi>=0.118.2 ; extra == 'tool-execution'
Requires-Dist: yamling ; extra == 'yaml'
Requires-Python: >=3.13
Project-URL: Code coverage, https://app.codecov.io/gh/phil65/schemez
Project-URL: Discussions, https://github.com/phil65/schemez/discussions
Project-URL: Documentation, https://phil65.github.io/schemez/
Project-URL: Issues, https://github.com/phil65/schemez/issues
Project-URL: Source, https://github.com/phil65/schemez
Provides-Extra: ai
Provides-Extra: codegen
Provides-Extra: markdown
Provides-Extra: storage
Provides-Extra: tool-execution
Provides-Extra: yaml
